benchmarks/__init__.py
benchmarks/benchmark_csf_vs_rsa.py
benchmarks/benchmark_performance.py
benchmarks/performance.py
csf/__init__.py
csf/core/__init__.py
csf/core/fractal_hash.py
csf/core/key_cache.py
csf/core/keys.py
csf/core/lattice.py
csf/core/memory.py
csf/core/randomness.py
csf/crypto/__init__.py
csf/crypto/adaptive_fractal.py
csf/crypto/decrypt.py
csf/crypto/encrypt.py
csf/crypto/encrypt_chunked.py
csf/crypto/signature.py
csf/crypto/streaming.py
csf/crypto/verification.py
csf/fractal/__init__.py
csf/fractal/decoder.py
csf/fractal/encoder.py
csf/fractal/visualizer.py
csf/fractal/noverraz/__init__.py
csf/fractal/noverraz/core.py
csf/fractal/noverraz/vectorized.py
csf/fractal/noverraz/tests/__init__.py
csf/fractal/noverraz/tests/test_noverraz.py
csf/pqc/__init__.py
csf/pqc/base.py
csf/pqc/dilithium.py
csf/pqc/kyber.py
csf/pqc/sphincs.py
csf/security/__init__.py
csf/security/constant_time.py
csf/security/entropy_check.py
csf/security/sidechannel.py
csf/security/validation.py
csf/security/wiping.py
csf/semantic/__init__.py
csf/semantic/combination.py
csf/semantic/embedding.py
csf/semantic/vectorizer.py
csf/tools/__init__.py
csf/tools/benchmark.py
csf/tools/keygen.py
csf/utils/__init__.py
csf/utils/compression.py
csf/utils/encoding.py
csf/utils/exceptions.py
csf/utils/format.py
csf/utils/serialization.py
csf_crypto-1.0.30.dist-info/METADATA
csf_crypto-1.0.30.dist-info/WHEEL
csf_crypto-1.0.30.dist-info/top_level.txt
csf_crypto-1.0.30.dist-info/RECORD
