Metadata-Version: 2.4
Name: csf-crypto
Version: 1.0.30
Summary: Post-quantum cryptographic framework with fractal encoding and semantic keys - resistant to quantum attacks
Home-page: https://github.com/iyotee/csf
Author: Jeremy Noverraz (based on an idea by Ivàn Àvalos AND JCZD (engrenage.ch))
Author-email: 
Maintainer: Jeremy Noverraz
License: MIT
Classifier: Development Status :: 4 - Beta
Classifier: Intended Audience :: Developers
Classifier: Topic :: Security :: Cryptography
Classifier: License :: OSI Approved :: MIT License
Classifier: Programming Language :: Python :: 3
Requires-Python: >=3.9
Requires-Dist: numpy>=1.24.0
Requires-Dist: scipy>=1.10.0
Requires-Dist: matplotlib>=3.7.0
Requires-Dist: msgpack>=1.0.0
Provides-Extra: pqc
Provides-Extra: dev
Requires-Dist: pytest>=7.0.0; extra == "dev"
Requires-Dist: pytest-cov>=4.0.0; extra == "dev"
Requires-Dist: mypy>=1.0.0; extra == "dev"
Requires-Dist: black>=23.0.0; extra == "dev"
Requires-Dist: flake8>=6.0.0; extra == "dev"
Provides-Extra: performance
Requires-Dist: numba>=0.58.0; extra == "performance"
Requires-Dist: cython>=3.0.0; extra == "performance"
Dynamic: home-page
Dynamic: maintainer
Dynamic: requires-python
